factoree_ai_connectors/__init__.py
factoree_ai_connectors/common/__init__.py
factoree_ai_connectors/common/system_params.py
factoree_ai_connectors/files/__init__.py
factoree_ai_connectors/files/file_types.py
factoree_ai_connectors/files/file_utils.py
factoree_ai_connectors/sensor/__init__.py
factoree_ai_connectors/sensor/sensor_info.py
factoree_ai_connectors/sink/__init__.py
factoree_ai_connectors/sink/s3/__init__.py
factoree_ai_connectors/sink/s3/s3_sink_connector.py
factoree_ai_connectors/sink/s3_client.py
factoree_ai_connectors/source/__init__.py
factoree_ai_connectors/source/s3/__init__.py
factoree_ai_connectors/source/s3/formatted_s3_source_connector.py
factoree_ai_connectors/source/s3/s3_source_connector.py
factoree_ai_connectors/source/sqs/__init__.py
factoree_ai_connectors/source/sqs/sqs_utils.py
factoree_ai_connectors/text/__init__.py
factoree_ai_connectors/text/text_parsers.py
factoree_ai_connectors/text/text_utils.py
factoree_ai_connectors-0.4.0.dist-info/LICENSE
factoree_ai_connectors-0.4.0.dist-info/WHEEL
factoree_ai_connectors-0.4.0.dist-info/METADATA
factoree_ai_connectors-0.4.0.dist-info/RECORD
