Metadata-Version: 2.1
Name: factoree-ai-connectors
Version: 0.4.0
Summary: 
Author: Uriah Ossin
Author-email: uriah@factoree.ai
Requires-Python: >=3.10,<4.0
Classifier: Programming Language :: Python :: 3
Classifier: Programming Language :: Python :: 3.10
Requires-Dist: boto3 (>=1.24.18,<2.0.0)
Requires-Dist: dotenv-config (>=0.1.4,<0.2.0)
Requires-Dist: flake8 (>=5.0.0,<6.0.0)
Requires-Dist: requests (>=2.28.0,<3.0.0)
